Workbook
Name Slicer_Relation: #N/A

Sheet Pivot Analysis
A3: Row Labels | B3: Sum of Confirmed Guests
A4: Bride | B4: 50
A5: Groom | B5: 62
A6: Grand Total | B6: 112

Sheet Guest Data
A1: Guests | B1: Invited By | C1: Relation | D1: RSVP | E1: Adults | F1: Kids | G1: Total Guests | H1: Confirmed Guests | I1: RSVP Status
A2: William Shelton | B2: Bride | C2: Colleague | D2: N | E2: 0 | F2: 0 | G2: =WeddingGuests[[#This Row],[Adults]]+WeddingGuests[[#This Row],[Kids]] -> 0 | H2: =IF(WeddingGuests[[#This Row],[RSVP]]="Y",WeddingGuests[[#This Row],[Total Guests]],0) -> 0 | I2: =IF(WeddingGuests[[#This Row],[RSVP]]="Y","Attending",IF(WeddingGuests[[#This Row],[RSVP]]="N","Not Attending","Unknown")) -> Not Attending
A3: Wanda Long | B3: Bride | C3: Colleague | D3: N | E3: 0 | F3: 0 | G3: =WeddingGuests[[#This Row],[Adults]]+WeddingGuests[[#This Row],[Kids]] -> 0 | H3: =IF(WeddingGuests[[#This Row],[RSVP]]="Y",WeddingGuests[[#This Row],[Total Guests]],0) -> 0 | I3: =IF(WeddingGuests[[#This Row],[RSVP]]="Y","Attending",IF(WeddingGuests[[#This Row],[RSVP]]="N","Not Attending","Unknown")) -> Not Attending
A4: Virginia Billingsley | B4: Bride | C4: Colleague | D4: N | E4: 0 | F4: 0 | G4: =WeddingGuests[[#This Row],[Adults]]+WeddingGuests[[#This Row],[Kids]] -> 0 | H4: =IF(WeddingGuests[[#This Row],[RSVP]]="Y",WeddingGuests[[#This Row],[Total Guests]],0) -> 0 | I4: =IF(WeddingGuests[[#This Row],[RSVP]]="Y","Attending",IF(WeddingGuests[[#This Row],[RSVP]]="N","Not Attending","Unknown")) -> Not Attending
A5: Susie Jones | B5: Bride | C5: Colleague | D5: N | E5: 0 | F5: 0 | G5: =WeddingGuests[[#This Row],[Adults]]+WeddingGuests[[#This Row],[Kids]] -> 0 | H5: =IF(WeddingGuests[[#This Row],[RSVP]]="Y",WeddingGuests[[#This Row],[Total Guests]],0) -> 0 | I5: =IF(WeddingGuests[[#This Row],[RSVP]]="Y","Attending",IF(WeddingGuests[[#This Row],[RSVP]]="N","Not Attending","Unknown")) -> Not Attending
A6: Stephen Bowen | B6: Bride | C6: Colleague | D6: N | E6: 0 | F6: 0 | G6: =WeddingGuests[[#This Row],[Adults]]+WeddingGuests[[#This Row],[Kids]] -> 0 | H6: =IF(WeddingGuests[[#This Row],[RSVP]]="Y",WeddingGuests[[#This Row],[Total Guests]],0) -> 0 | I6: =IF(WeddingGuests[[#This Row],[RSVP]]="Y","Attending",IF(WeddingGuests[[#This Row],[RSVP]]="N","Not Attending","Unknown")) -> Not Attending
A7: Shirley Irwin | B7: Bride | C7: Colleague | D7: Y | E7: 2 | F7: 0 | G7: =WeddingGuests[[#This Row],[Adults]]+WeddingGuests[[#This Row],[Kids]] -> 2 | H7: =IF(WeddingGuests[[#This Row],[RSVP]]="Y",WeddingGuests[[#This Row],[Total Guests]],0) -> 2 | I7: =IF(WeddingGuests[[#This Row],[RSVP]]="Y","Attending",IF(WeddingGuests[[#This Row],[RSVP]]="N","Not Attending","Unknown")) -> Attending
A8: Shaun Elliot | B8: Bride | C8: Colleague | D8: Y | E8: 1 | F8: 0 | G8: =WeddingGuests[[#This Row],[Adults]]+WeddingGuests[[#This Row],[Kids]] -> 1 | H8: =IF(WeddingGuests[[#This Row],[RSVP]]="Y",WeddingGuests[[#This Row],[Total Guests]],0) -> 1 | I8: =IF(WeddingGuests[[#This Row],[RSVP]]="Y","Attending",IF(WeddingGuests[[#This Row],[RSVP]]="N","Not Attending","Unknown")) -> Attending
A9: Ronald Maclean | B9: Bride | C9: Colleague | D9: N | E9: 0 | F9: 0 | G9: =WeddingGuests[[#This Row],[Adults]]+WeddingGuests[[#This Row],[Kids]] -> 0 | H9: =IF(WeddingGuests[[#This Row],[RSVP]]="Y",WeddingGuests[[#This Row],[Total Guests]],0) -> 0 | I9: =IF(WeddingGuests[[#This Row],[RSVP]]="Y","Attending",IF(WeddingGuests[[#This Row],[RSVP]]="N","Not Attending","Unknown")) -> Not Attending
A10: Robert Martin | B10: Bride | C10: Colleague | D10: N | E10: 0 | F10: 0 | G10: =WeddingGuests[[#This Row],[Adults]]+WeddingGuests[[#This Row],[Kids]] -> 0 | H10: =IF(WeddingGuests[[#This Row],[RSVP]]="Y",WeddingGuests[[#This Row],[Total Guests]],0) -> 0 | I10: =IF(WeddingGuests[[#This Row],[RSVP]]="Y","Attending",IF(WeddingGuests[[#This Row],[RSVP]]="N","Not Attending","Unknown")) -> Not Attending
A11: Richard Greene | B11: Bride | C11: Colleague | D11: N | E11: 0 | F11: 0 | G11: =WeddingGuests[[#This Row],[Adults]]+WeddingGuests[[#This Row],[Kids]] -> 0 | H11: =IF(WeddingGuests[[#This Row],[RSVP]]="Y",WeddingGuests[[#This Row],[Total Guests]],0) -> 0 | I11: =IF(WeddingGuests[[#This Row],[RSVP]]="Y","Attending",IF(WeddingGuests[[#This Row],[RSVP]]="N","Not Attending","Unknown")) -> Not Attending
A12: Mary Lee Rumage | B12: Bride | C12: Colleague | D12: N | E12: 0 | F12: 0 | G12: =WeddingGuests[[#This Row],[Adults]]+WeddingGuests[[#This Row],[Kids]] -> 0 | H12: =IF(WeddingGuests[[#This Row],[RSVP]]="Y",WeddingGuests[[#This Row],[Total Guests]],0) -> 0 | I12: =IF(WeddingGuests[[#This Row],[RSVP]]="Y","Attending",IF(WeddingGuests[[#This Row],[RSVP]]="N","Not Attending","Unknown")) -> Not Attending
A13: Lucy Pulliam | B13: Bride | C13: Colleague | D13: N | E13: 0 | F13: 0 | G13: =WeddingGuests[[#This Row],[Adults]]+WeddingGuests[[#This Row],[Kids]] -> 0 | H13: =IF(WeddingGuests[[#This Row],[RSVP]]="Y",WeddingGuests[[#This Row],[Total Guests]],0) -> 0 | I13: =IF(WeddingGuests[[#This Row],[RSVP]]="Y","Attending",IF(WeddingGuests[[#This Row],[RSVP]]="N","Not Attending","Unknown")) -> Not Attending
... A127: Betty Weaver | B127: Groom | C127: Friend | D127: Y | E127: 2 | F127: 0 | G127: =WeddingGuests[[#This Row],[Adults]]+WeddingGuests[[#This Row],[Kids]] -> 2 | H127: =IF(WeddingGuests[[#This Row],[RSVP]]="Y",WeddingGuests[[#This Row],[Total Guests]],0) -> 2 | I127: =IF(WeddingGuests[[#This Row],[RSVP]]="Y","Attending",IF(WeddingGuests[[#This Row],[RSVP]]="N","Not Attending","Unknown")) -> Attending

Sheet Attendance Summary
A1: Wedding Guest Attendance Analysis
D2: Invited By | E2: Attending Guest | G2: Data Validation
A3: Total Attending Adults | B3: =SUMIF('Guest Data'!D:D, "Y", 'Guest Data'!E:E) -> 102 | D3: Bride | E3: =SUMIFS('Guest Data'!E:E,'Guest Data'!B:B,D3,'Guest Data'!D:D,"Y")+SUMIFS('Guest Data'!F:F,'Guest Data'!B:B,D3,'Guest Data'!D:D,"Y") -> 50 | G3: Confirmed Guests Check | H3: =SUM(WeddingGuests[Confirmed Guests]) -> 112
A4: Total Attending Children | B4: =SUMIF('Guest Data'!D:D,"Y",'Guest Data'!F:F) -> 10 | D4: Groom | E4: =SUMIFS('Guest Data'!E:E,'Guest Data'!B:B,D4,'Guest Data'!D:D,"Y")+SUMIFS('Guest Data'!F:F,'Guest Data'!B:B,D4,'Guest Data'!D:D,"Y") -> 62 | G4: Original Attendance Total | H4: =B5 -> 112
A5: Total Attending Guests | B5: =SUM(B3:B4) -> 112 | G5: Validation Result | H5: =IF(H3=H4,"PASS","CHECK DATA") -> PASS
A7: Adult Reception Cost | B7: =B3*67.5 -> 6885 | D7: Guest Type | E7: Number Attending
A8: Child Reception Cost | B8: =B4*(67.5*70%) -> 472.5 | D8: Adults | E8: =B3 -> 102
A9: Reception Subtotal | B9: =SUM(B7:B8) -> 7357.5 | D9: Children | E9: =B4 -> 10
A10: Sales Tax (8.25%) | B10: =B9*8.25% -> 606.99375
A11: Total Reception Cost | B11: =SUM(B9:B10) -> 7964.4937
D12: Relationship | E12: Confirmed Guests
D13: Colleague | E13: =SUMIFS(WeddingGuests[Confirmed Guests],WeddingGuests[Relation],D13) -> 45
D14: Family | E14: =SUMIFS(WeddingGuests[Confirmed Guests],WeddingGuests[Relation],D14) -> 24
D15: Friend | E15: =SUMIFS(WeddingGuests[Confirmed Guests],WeddingGuests[Relation],D15) -> 43
D16: Total | E16: =SUM(E13:E15) -> 112

Sheet Dashboard
A1: WEDDING GUEST ANALYTICS DASHBOARD
A2: Jane & Joe | Guest Attendance and Reception Budget
A4: Confirmed Guests | D4: Attending Adults | G4: Attending Children
A5: =SUM(WeddingGuests[Confirmed Guests]) -> 112 | D5: ='Attendance Summary'!B3 -> 102 | G5: ='Attendance Summary'!B4 -> 10
A8: Attending RSVPs | D8: Declined RSVPs | G8: Total Reception Cost
A9: =COUNTIF(WeddingGuests[RSVP],"Y") -> 59 | D9: =COUNTIF(WeddingGuests[RSVP],"N") -> 67 | G9: ='Attendance Summary'!B11 -> 7964.4937
A12: RSVP Acceptance Rate
A13: =COUNTIF(WeddingGuests[RSVP],"Y")/COUNTA(WeddingGuests[RSVP]) -> 0.46825397
A15: Attendance Overview
A34: Guest Relationship Analysis
A54: Interactive Filters
A55: Select a relationship category to filter the Interactive Attendance by Inviter chart. Other metrics display overall totals.
